README.rst
setup.py
xunbao_models/__init__.py
xunbao_models/admin.py
xunbao_models/advertising.py
xunbao_models/area.py
xunbao_models/commodity.py
xunbao_models/main.py
xunbao_models/master.py
xunbao_models/merchant.py
xunbao_models/message.py
xunbao_models/news.py
xunbao_models/user.py
xunbao_models/video.py
xunbao_models.egg-info/PKG-INFO
xunbao_models.egg-info/SOURCES.txt
xunbao_models.egg-info/dependency_links.txt
xunbao_models.egg-info/top_level.txt